{
    "relationship": [
      { "key": "Father", "value": "Father / પિતા" },
      { "key": "Mother", "value": "Mother / માતા" },
      { "key": "Husband", "value": "Husband / પતિ" },
      { "key": "Wife", "value": "Wife / પત્ની" },
      { "key": "Son", "value": "Son / પુત્ર" },
      { "key": "Daughter", "value": "Daughter / પુત્રી" },
      { "key": "GrandSon", "value": "Grand son / પૌત્ર" },
      { "key": "GrandDaughter", "value": "Grand daughter / પૌત્રી" },
      { "key": "Brother", "value": "Brother / ભાઈ" },
      { "key": "Sister", "value": "Sister / બહેન" },
      { "key": "Grandfather", "value": "Grandfather  / દાદા" },
      { "key": "Grandmother", "value": "Grandmother  / દાદી" },
      { "key": "Daughter-in-law", "value": "Daughter-in-law  / પુત્રવધૂ" }
    ],
    
    "relationshipDetails": [
      { "key": "Ramesh's Father", "value": "Father" },
      { "key": "Ramesh's Mother", "value": "Mother","root":0 },
      { "key": "Ramesh's Wife", "value": "Wife","root":1 },
      { "key": "Ramesh's Child", "value": "Child","root":2 },
      { "key": "Mother", "value": "Mother / માતા" },
      { "key": "Husband", "value": "Husband / પતિ" },
      { "key": "Wife", "value": "Wife / પત્ની" },
      { "key": "Son", "value": "Son / પુત્ર" },
      { "key": "Daughter", "value": "Daughter / પુત્રી" },
      { "key": "GrandSon", "value": "Grand son / પૌત્ર" },
      { "key": "GrandDaughter", "value": "Grand daughter / પૌત્રી" },
      { "key": "Brother", "value": "Brother / ભાઈ" },
      { "key": "Sister", "value": "Sister / બહેન" },
      { "key": "Grandfather", "value": "Grandfather  / દાદા" },
      { "key": "Grandmother", "value": "Grandmother  / દાદી" },
      { "key": "Daughter-in-law", "value": "Daughter-in-law  / પુત્રવધૂ" }
    ]
  }
  